LICENSE.txt
MANIFEST.in
README.rst
VERSION.txt
setup.cfg
setup.py
chunked_upload/__init__.py
chunked_upload/admin.py
chunked_upload/constants.py
chunked_upload/exceptions.py
chunked_upload/models.py
chunked_upload/response.py
chunked_upload/settings.py
chunked_upload/tests.py
chunked_upload/views.py
chunked_upload/management/__init__.py
chunked_upload/management/commands/__init__.py
chunked_upload/management/commands/delete_expired_uploads.py
chunked_upload/migrations/0001_initial.py
chunked_upload/migrations/__init__.py
django4_chunked_upload.egg-info/PKG-INFO
django4_chunked_upload.egg-info/SOURCES.txt
django4_chunked_upload.egg-info/dependency_links.txt
django4_chunked_upload.egg-info/top_level.txt