Metadata-Version: 2.1
Name: django4-chunked-upload
Version: 2.0.1
Summary: Upload large files to Django in multiple chunks, with the ability to resume if the upload is interrupted. Updated to support newer versions on Django. Based on the project of Julio M Alegria.
Home-page: https://github.com/fredito1212/django-chunked-upload
Download-URL: https://github.com/fredito1212/django-chunked-upload/tarball/2.0.1
Author: Julio M Alegria & Jesus A Bravo
Author-email: isc.alfredobravo@gmail.com
License: MIT-Zero
License-File: LICENSE.txt
